LICENSE.txt
README.rst
setup.cfg
setup.py
test9191/__init__.py
test9191/myprofile.py
test9191.egg-info/PKG-INFO
test9191.egg-info/SOURCES.txt
test9191.egg-info/dependency_links.txt
test9191.egg-info/top_level.txt